{
    "default_model": "LEOSAM_helloworld_XL_v60.safetensors",
    "default_refiner": "None",
    "default_refiner_switch": 0.5,
    "default_loras_min_weight": -5,
    "default_loras_max_weight": 5,
    "default_loras": [
        [
            true,
            "Detail_Tweaker_XL.safetensors",
            1.0
        ],
        [
            true,
            "None",
            1.0
        ],
        [
            true,
            "None",
            1.0
        ],
        [
            true,
            "None",
            1.0
        ],
        [
            true,
            "None",
            1.0
        ]
    ],
    "default_max_lora_number": 10,
    "default_cfg_scale": 8.0,
    "default_sample_sharpness": 2.0,
    "default_sampler": "dpmpp_2m_sde_gpu",
    "default_scheduler": "karras",
    "default_performance": "Speed",
    "default_prompt": "",
    "default_prompt_negative": "",
    "default_styles": [],
    "default_aspect_ratio": "832*1216",
    "checkpoint_downloads": {
        "LEOSAM_helloworld_XL_v60.safetensors": "https://civitai.com/api/download/models/456751?type=Model&format=SafeTensor&size=pruned&fp=fp16"
    },
    "embeddings_downloads": {},
    "lora_downloads": {
        "Detail_Tweaker_XL.safetensors": "https://civitai.com/api/download/models/135867?type=Model&format=SafeTensor"
    },
    "previous_default_models": ["realisticStockPhoto_v10.safetensors"]
}
